{
	"info": {
		"_postman_id": "86c8f9e0-cbf4-4900-9ccb-0f791c5c5b64",
		"name": "Biodata",
		"schema": "https://schema.getpostman.com/json/collection/v2.1.0/collection.json",
		"_exporter_id": "11108847",
		"_collection_link": "https://orange-shuttle-39637.postman.co/workspace/My-Workspace~19abc2a1-782c-4d73-8aa2-d8ce678a2725/collection/11108847-86c8f9e0-cbf4-4900-9ccb-0f791c5c5b64?action=share&source=collection_link&creator=11108847"
	},
	"item": [
		{
			"name": "Auth",
			"item": [
				{
					"name": "Store",
					"request": {
						"method": "POST",
						"header": [],
						"body": {
							"mode": "raw",
							"raw": "{\r\n    \"username\":\"rangga\",\r\n    \"password\":\"mitsuha\",\r\n    \"name\":\"Rangga Adi Pratama\",\r\n    \"email\":\"masterrangga@gmail.com\"\r\n}",
							"options": {
								"raw": {
									"language": "json"
								}
							}
						},
						"url": {
							"raw": "{{url}}auth/register",
							"host": [
								"{{url}}auth"
							],
							"path": [
								"register"
							]
						}
					},
					"response": []
				}
			]
		}
	]
}